Metadata-Version: 2.1
Name: openapi2omg
Version: 0.1.0
Summary: A tool to convert an OpenAPI spec to an OMG spec
Home-page: https://github.com/microservices/openapi2omg
Author: Storyscript
Author-email: support@storyscript.io
License: UNKNOWN
Platform: UNKNOWN
Classifier: Programming Language :: Python :: 3
Classifier: License :: OSI Approved :: MIT License
Classifier: Operating System :: OS Independent
